[{"track_id":"20181024_d1_0830_0900_1"," lat":" 37.977391"," lon":" 23.737688"," speed":" 4.9178"," lon_acc":" 0.0518"," lat_acc":" -0.0299"," time":" 0.000000"},{"track_id":"20181024_d1_0830_0900_1"," lat":" 37.977391"," lon":" 23.737688"," speed":" 4.9207"," lon_acc":" -0.0124"," lat_acc":" -0.0354"," time":" 0.040000"},{"track_id":"20181024_d1_0830_0900_1"," lat":" 37.977391"," lon":" 23.737688"," speed":" 4.9160"," lon_acc":" -0.0519"," lat_acc":" -0.0413"," time":" 0.080000"},{"track_id":"20181024_d1_0830_0900_1"," lat":" 37.977390"," lon":" 23.737688"," speed":" 4.9057"," lon_acc":" -0.0914"," lat_acc":" -0.0478"," time":" 0.120000"},{"track_id":"20181024_d1_0830_0900_1"," lat":" 37.977390"," lon":" 23.737689"," speed":" 4.8871"," lon_acc":" -0.1679"," lat_acc":" -0.0550"," time":" 0.160000"}]